secrets_sdk/__init__.py
secrets_sdk/audit.py
secrets_sdk/bootstrap.py
secrets_sdk/client.py
secrets_sdk/context.py
secrets_sdk/errors.py
secrets_sdk/py.typed
secrets_sdk/sanitize.py
secrets_sdk/secret_uri.py
secrets_sdk/vault_client.py
secrets_sdk/grants/grant_cache.py
secrets_sdk/services/secret_policy_service.py
secrets_sdk/vault_strategies/base_vault_strategy.py
secrets_sdk/vault_strategies/errors.py
secrets_sdk/vault_strategies/hashicorp_vault_strategy.py
secrets_sdk/vault_strategies/openbao_vault_strategy.py
empowernow_secrets_sdk-0.2.0.dist-info/METADATA
empowernow_secrets_sdk-0.2.0.dist-info/WHEEL
empowernow_secrets_sdk-0.2.0.dist-info/top_level.txt
empowernow_secrets_sdk-0.2.0.dist-info/RECORD
