Metadata-Version: 2.4
Name: empowernow-secrets-sdk
Version: 0.2.0
Summary: In-process Canonical Secret URI client with PEP enforcement and Vault providers
Author: EmpowerNow
Requires-Python: >=3.11
Requires-Dist: tenacity>=8.2.3
Requires-Dist: cachetools>=5.3.3
Requires-Dist: httpx>=0.25.0
Requires-Dist: opentelemetry-api>=1.20.0
Provides-Extra: dev
Requires-Dist: pytest>=8.2.0; extra == "dev"
Requires-Dist: pytest-asyncio>=0.23.8; extra == "dev"
